{
  "id": "EastAsia",
  "name": "East Asia",
  "translation_key": "map.eastasia",
  "categories": ["asia"],
  "multiplayer_frequency": 5,
  "nations": [
    {
      "coordinates": [1150, 660],
      "name": "Hokkaido",
      "flag": "jp"
    },
    {
      "coordinates": [1005, 843],
      "name": "Tohoku",
      "flag": "jp"
    },
    {
      "coordinates": [858, 1045],
      "name": "Chubu",
      "flag": "jp"
    },
    {
      "coordinates": [948, 1037],
      "name": "Kanto",
      "flag": "jp"
    },
    {
      "coordinates": [1162, 154],
      "name": "Sakhalin",
      "flag": "Sakhalin"
    },
    {
      "coordinates": [571, 1116],
      "name": "Chugoku",
      "flag": "jp"
    },
    {
      "coordinates": [595, 1190],
      "name": "Shikoku",
      "flag": "jp"
    },
    {
      "coordinates": [450, 1234],
      "name": "Kyushu",
      "flag": "jp"
    },
    {
      "coordinates": [274, 1058],
      "name": "South Korea",
      "flag": "kr"
    },
    {
      "coordinates": [160, 841],
      "name": "North Korea",
      "flag": "kp"
    },
    {
      "coordinates": [15, 795],
      "name": "China",
      "flag": "cn"
    },
    {
      "coordinates": [230, 75],
      "name": "Russia",
      "flag": "ru"
    },
    {
      "coordinates": [898, 923],
      "name": "Sado Island",
      "flag": "jp"
    },
    {
      "coordinates": [592, 1031],
      "name": "Oki Islands",
      "flag": "jp"
    },
    {
      "coordinates": [741, 1108],
      "name": "Kyoto",
      "flag": "jp"
    },
    {
      "coordinates": [219, 972],
      "name": "Seoul",
      "flag": "kr"
    },
    {
      "coordinates": [976, 1073],
      "name": "Tokyo",
      "flag": "jp"
    },
    {
      "coordinates": [911, 1079],
      "name": "Mount Fuji",
      "flag": "jp"
    },
    {
      "coordinates": [1298, 564],
      "name": "Shiretoko Peninsula",
      "flag": "jp"
    },
    {
      "coordinates": [435, 1311],
      "name": "Sakurajima",
      "flag": "jp"
    },
    {
      "coordinates": [275, 1614],
      "name": "Okinawa",
      "flag": "jp"
    },
    {
      "coordinates": [731, 1115],
      "name": "Kinki",
      "flag": "jp"
    }
  ]
}
